[
  {
    "angular_rate_norm_radps": 0.002028383481658012,
    "failure_modes": "hard_touchdown",
    "horizontal_touchdown_velocity_mps": 0.048505168939380776,
    "label": "overspeed_assist_focus_blended",
    "landing_position_error_m": 0.1214814363546394,
    "success": false,
    "tilt_angle_deg": 0.08636230438211524,
    "vertical_touchdown_velocity_mps": -4.113545932795983
  },
  {
    "angular_rate_norm_radps": 0.002036164760724194,
    "failure_modes": "hard_touchdown",
    "horizontal_touchdown_velocity_mps": 0.04757923781834176,
    "label": "near_ground_touchdown",
    "landing_position_error_m": 0.12305233875939532,
    "success": false,
    "tilt_angle_deg": 0.0862410099898698,
    "vertical_touchdown_velocity_mps": -4.111330373837729
  }
]